rbpop/__init__.py
rbpop/ui_demo.py
rbpop/utils.py
rbpop/prefab/__init__.py
rbpop/prefab/message.py
rbpop/win/__init__.py
rbpop/win/manager.py
rbpop/win/popped.py
rbpop-0.3.1.dist-info/METADATA
rbpop-0.3.1.dist-info/WHEEL
rbpop-0.3.1.dist-info/top_level.txt
rbpop-0.3.1.dist-info/RECORD
